xpress_lz77-1.0.1.dist-info/METADATA
xpress_lz77-1.0.1.dist-info/WHEEL
xpress_lz77-1.0.1.dist-info/licenses/LICENSE
xpress_lz77/__init__.py
xpress_lz77/xpress_lz77.pypy39-pp73-s390x-linux-gnu.so
xpress_lz77-1.0.1.dist-info/RECORD
